NeuralWaveFunction/1DTFIM.py
NeuralWaveFunction/__init__.py
NeuralWaveFunction-0.0.1rc2.dist-info/LICENSE
NeuralWaveFunction-0.0.1rc2.dist-info/METADATA
NeuralWaveFunction-0.0.1rc2.dist-info/WHEEL
NeuralWaveFunction-0.0.1rc2.dist-info/top_level.txt
NeuralWaveFunction-0.0.1rc2.dist-info/RECORD
