Metadata-Version: 2.1
Name: NeuralWaveFunction
Version: 0.0.1rc2
Summary: VMC with neural networks as test functions
Home-page: https://gitlab.physik.uni-muenchen.de/A.Dautovic/neuralwavefunction
Author: Adnan Dautovic
Author-email: A.Dautovic@phyik.uni-muenchen.de
License: UNKNOWN
Platform: UNKNOWN
Classifier: Development Status :: 1 - Planning
Classifier: Programming Language :: Python :: 3
Classifier: License :: OSI Approved :: GNU General Public License v3 (GPLv3)
Classifier: Operating System :: OS Independent
